{"643783537779339266": ["6:48 AM - 15 Sep 2015", "#ISIS Leaders Praise #KimDavis – First Female to Win ISIS Courage Award… http://nationalreport.net/isis-leaders-praise-kim-davis-first-female-win-isis-courage-award/ …pic.twitter.com/5BvN5dFbZD"], "643783549124935680": ["6:48 AM - 15 Sep 2015", "#ISIS Leaders Praise #KimDavis – First Female to Win ISIS Courage Award… http://nationalreport.net/isis-leaders-praise-kim-davis-first-female-win-isis-courage-award/ …pic.twitter.com/ksDLlcWWzm"], "643783561061863424": ["6:48 AM - 15 Sep 2015", "#ISIS Leaders Praise #KimDavis – First Female to Win ISIS Courage Award… http://nationalreport.net/isis-leaders-praise-kim-davis-first-female-win-isis-courage-award/ …pic.twitter.com/UKqeo05uww"], "643825386917396480": ["9:35 AM - 15 Sep 2015", "ISIS Leaders Praise Kim Davis – First Female to Win ISIS Courage Award http://fb.me/7NdoxJ04N "], "643827780728127488": ["9:44 AM - 15 Sep 2015", "ISIS Leaders Praise Kim Davis – First Female to Win ISIS Courage Award http://fb.me/38ZV67W0e "], "643831935509360640": ["10:01 AM - 15 Sep 2015", "ISIS Leaders Praise Kim Davis – First Female to Win ISIS Courage Award http://fb.me/L8kkW6as "], "643844446849736704": ["10:50 AM - 15 Sep 2015", "ISIS Leaders Praise Kim Davis – First Female to Win ISIS Courage Award | National Report http://nationalreport.net/isis-leaders-praise-kim-davis-first-female-win-isis-courage-award/ … via @wpusta"], "643847807485497344": [null, null], "643862837924888576": ["12:03 PM - 15 Sep 2015", "ISIS Leaders Praise Kim Davis – First Female to Win ISIS Courage Award - USAToday http://usatoday.com.co/isis-leaders-praise-kim-davis-first-female-to-win-isis-courage-award/ …"], "643874403193909248": ["12:49 PM - 15 Sep 2015", "ISIS Leaders Praise Kim Davis – First Female to Win ISIS Courage Award | National Report http://nationalreport.net/isis-leaders-praise-kim-davis-first-female-win-isis-courage-award/ … via @wpusta"], "643892223705284608": [null, null], "643896278682836992": ["2:16 PM - 15 Sep 2015", "ISIS Leaders Praise Kim Davis – First Female to Win ISIS Courage Award http://fake.trendolizer.com/2015/09/isis-leaders-praise-kim-davis-first-female-to-win-isis-courage-award.html …pic.twitter.com/AdwreVm33D"], "643903342259904512": ["2:44 PM - 15 Sep 2015", "ISIS Leaders Praise Kim Davis – First Female to Win ISIS Courage Award - USAToday http://usatoday.com.co/isis-leaders-praise-kim-davis-first-female-to-win-isis-courage-award/ …"], "643908713103925248": [null, null], "643909204680548352": ["3:08 PM - 15 Sep 2015", "#KimDavis honored by #ISIS #ShariaLaw http://nationalreport.net/isis-leaders-praise-kim-davis-first-female-win-isis-courage-award/ …"], "643909753207455745": ["3:10 PM - 15 Sep 2015", "#KimDavis honored by #ISIS #sharia #ShariaLaw\nhttp://nationalreport.net/isis-leaders-praise-kim-davis-first-female-win-isis-courage-award/ …"], "643923339161939968": ["4:04 PM - 15 Sep 2015", "ISIS Leaders Praise Kim Davis – First Female to Win ISIS Courage Award - USAToday http://fb.me/7thQWiQNh "], "643938790193676288": ["5:05 PM - 15 Sep 2015", "#ISIS Leaders Praise #KimDavis – First Female to Win #ISIS Courage Award http://nationalreport.net/isis-leaders-praise-kim-davis-first-female-win-isis-courage-award/ …"], "643942893183479809": ["5:22 PM - 15 Sep 2015", "ISIS Leaders Praise Kim Davis – First Female to Win ISIS Courage Award http://fb.me/4GZusSwPA "], "643943325192585216": ["5:23 PM - 15 Sep 2015", "\nISIS Leaders Praise Kim Davis – First Female to Win ISIS Courage Award | National Report http://nationalreport.net/isis-leaders-praise-kim-davis-first-female-win-isis-courage-award/ … via @wpusta"], "643943526741315584": [null, null], "643981473062653952": ["7:55 PM - 15 Sep 2015", "ISIS Leaders Praise Kim Davis – First Female to Win ISIS Courage Award - USAToday http://fb.me/48Dy8ZbQ7 "], "643984829474861057": ["8:08 PM - 15 Sep 2015", "@GeologyReport \nISIS leader Abu Ali al-Anbari said today Kim Davis will be the very first female to win the prestigious ‘ISIS Courage Award’"], "643998662138437632": ["9:03 PM - 15 Sep 2015", "ISIS Leaders Praise Kim Davis – First Female to Win ISIS Courage Award - USAToday http://usatoday.com.co/isis-leaders-praise-kim-davis-first-female-to-win-isis-courage-award/ …"], "644000619691409408": [null, null], "644001956747452416": [null, null], "644003807987388417": ["9:24 PM - 15 Sep 2015", "ISIS Leaders Praise Kim Davis – First Female to Win ISIS Courage Award - USAToday http://usatoday.com.co/isis-leaders-praise-kim-davis-first-female-to-win-isis-courage-award/ …"], "644005760494665728": ["9:31 PM - 15 Sep 2015", "ISIS Leaders Praise Kim Davis – First Female to Win ISIS Courage Award - USAToday http://usatoday.com.co/isis-leaders-praise-kim-davis-first-female-to-win-isis-courage-award/ …"], "644009558789197824": ["9:46 PM - 15 Sep 2015", "ISIS Leaders Praise Kim Davis – First Female to Win ISIS Courage Award - USAToday http://usatoday.com.co/isis-leaders-praise-kim-davis-first-female-to-win-isis-courage-award/ …"], "644009730613071872": ["9:47 PM - 15 Sep 2015", "ISIS Leaders Praise Kim Davis – First Female to Win ISIS Courage Award - USAToday http://tmblr.co/ZrU7Hy1uKh1pn "], "644010186999472129": ["9:49 PM - 15 Sep 2015", "ISIS Leaders Praise Kim Davis – First Female to Win ISIS Courage Award  http://www.redflagnews.com/headlines-2015/isis-leaders-praise-kim-davis-first-female-to-win-isis-courage-award …"], "644016651319574529": ["10:15 PM - 15 Sep 2015", "ISIS Leaders Praise Kim Davis – First Female to Win ISIS Courage Award - See more at: http://ln.is/nationalreport.net/i/hSLL6 …"], "644039177311404032": ["11:44 PM - 15 Sep 2015", "ISIS Leaders Praise Kim Davis – First Female to Win ISIS Courage Award - USAToday http://fb.me/6NDcOY93V "], "644062278967496704": [null, null], "644107469648625664": ["4:16 AM - 16 Sep 2015", "Not satire. http://fb.me/7lsfTRw6o "], "644111646856581121": ["4:32 AM - 16 Sep 2015", "ISIS Leaders Praise Kim Davis – First Female to Win ISIS Courage Award - USAToday http://fb.me/22KnhmGQy "], "644125193925869568": ["5:26 AM - 16 Sep 2015", "ISIS Leaders Praise Kim Davis – First Female to Win ISIS Courage Award - USAToday http://usatoday.com.co/isis-leaders-praise-kim-davis-first-female-to-win-isis-courage-award/ …"], "644132017580453888": [null, null], "644134065323511808": ["6:01 AM - 16 Sep 2015", "ISIS Leaders Praise Kim Davis – First Female to Win ISIS Courage Award - USAToday http://fb.me/1XDcV6QKO "], "644134701788233728": ["6:04 AM - 16 Sep 2015", "ISIS Leaders Praise Kim Davis – First Female to Win ISIS Courage Award - USAToday http://fb.me/7zhPEeNHq "], "644145509968560128": ["6:47 AM - 16 Sep 2015", "ISIS Leaders Praise Kim Davis – First Female to Win ISIS Courage Award | National Report http://nationalreport.net/isis-leaders-praise-kim-davis-first-female-win-isis-courage-award/ …"], "644146894868979712": ["6:52 AM - 16 Sep 2015", "ISIS Leaders Praise Kim Davis – First Female to Win ISIS Courage Award  http://www.redflagnews.com/headlines-2015/isis-leaders-praise-kim-davis-first-female-to-win-isis-courage-award …"], "644156635703836672": ["7:31 AM - 16 Sep 2015", "ISIS Leaders Praise Kim Davis – First Female to Win ISIS Courage Award - USAToday http://usatoday.com.co/isis-leaders-praise-kim-davis-first-female-to-win-isis-courage-award/ …"], "644170644452700160": [null, null], "644175439506739200": ["8:46 AM - 16 Sep 2015", "WHAT?!?!? @vickitiahrt @dglasscock @RepToddTiahrt http://usatoday.com.co/isis-leaders-praise-kim-davis-first-female-to-win-isis-courage-award/ …"], "644182448004182016": ["9:13 AM - 16 Sep 2015", "ISIS Leaders Praise Kim Davis – First Female to Win ISIS Courage Award - USAToday http://fb.me/3s13PesTI "], "644182898933911553": ["9:15 AM - 16 Sep 2015", "ISIS Leaders Praise Kim Davis – First Female to Win ISIS Courage Award - USAToday http://usatoday.com.co/isis-leaders-praise-kim-davis-first-female-to-win-isis-courage-award/ …"], "644188445762457600": ["9:37 AM - 16 Sep 2015", "#Isis applauds #KimDavis:  http://nationalreport.net/isis-leaders-praise-kim-davis-first-female-win-isis-courage-award/ …"], "644192073206394880": ["9:52 AM - 16 Sep 2015", "ISIS Leaders Praise Kim Davis – First Female to Win ISIS Courage Award | National Report http://nationalreport.net/isis-leaders-praise-kim-davis-first-female-win-isis-courage-award/ … via @wpusta"], "644199727496474624": ["10:22 AM - 16 Sep 2015", "Lol-\n\"ISIS leader Abu Ali al-Anbari released a statement today saying Kim Davis will be the very first female to... http://fb.me/426pYCieQ "], "644211138733936640": ["11:07 AM - 16 Sep 2015", "ISIS Leaders Praise Kim Davis – First Female to Win ISIS Courage Award - USAToday http://usatoday.com.co/isis-leaders-praise-kim-davis-first-female-to-win-isis-courage-award/ …"], "644222764052836353": ["11:54 AM - 16 Sep 2015", "ISIS Leaders Praise Kim Davis – First Female to Win ISIS Courage Award - USAToday http://usatoday.com.co/isis-leaders-praise-kim-davis-first-female-to-win-isis-courage-award/ …"], "644223689190305792": ["11:57 AM - 16 Sep 2015", "ISIS Leaders Praise Kim Davis – First Female to Win ISIS Courage Award - USAToday http://usatoday.com.co/isis-leaders-praise-kim-davis-first-female-to-win-isis-courage-award/ …"], "644228621830369280": ["12:17 PM - 16 Sep 2015", "Priceless\nhttp://usatoday.com.co/isis-leaders-praise-kim-davis-first-female-to-win-isis-courage-award/ …"], "644238881441755136": ["12:58 PM - 16 Sep 2015", "ISIS Leaders Praise Kim Davis – First Female to Win ISIS Courage Award - USAToday http://usatoday.com.co/isis-leaders-praise-kim-davis-first-female-to-win-isis-courage-award/ …"], "644239674123382785": ["1:01 PM - 16 Sep 2015", "ISIS Leaders Praise Kim Davis – First Female to Win ISIS Courage Award - USAToday http://fb.me/6PJ94KBT3 "], "644240055104499712": ["1:02 PM - 16 Sep 2015", "ISIS Leaders Praise Kim Davis – First Female to Win ISIS Courage Award - USAToday http://usatoday.com.co/isis-leaders-praise-kim-davis-first-female-to-win-isis-courage-award/ …"], "644242703966859264": ["1:13 PM - 16 Sep 2015", "ISIS Leaders Praise Kim Davis – First Female to Win ISIS Courage Award - USAToday http://fb.me/3iOzx414s "], "644243439098417152": ["1:16 PM - 16 Sep 2015", "ISIS Leaders Praise Kim Davis – First Female to Win ISIS Courage Award - USAToday http://fb.me/7r2Mlb3iN "], "644255342642094080": ["2:03 PM - 16 Sep 2015", "#NoThanks! #BirdsOfaFeather! #ISIS Leaders Praise Kim Davis – First Female to Win ISIS Courage Award - USAToday http://usatoday.com.co/isis-leaders-praise-kim-davis-first-female-to-win-isis-courage-award/ …"], "644256197952954368": ["2:07 PM - 16 Sep 2015", "ISIS Leaders Praise Kim Davis – First Female to Win ISIS Courage Award - USAToday http://usatoday.com.co/isis-leaders-praise-kim-davis-first-female-to-win-isis-courage-award/ …"], "644262890950672384": [null, null], "644278233634967552": ["3:34 PM - 16 Sep 2015", "FALSE: ISIS Leaders Praise Kim Davis – First Female to Win ISIS Courage Award http://hoax.trendolizer.com/2015/09/false-isis-leaders-praise-kim-davis-first-female-to-win-isis-courage-award.html …pic.twitter.com/sxqNXSfzVU"], "644279351572234240": ["3:39 PM - 16 Sep 2015", "ISIS Leaders Praise Kim Davis – First Female to Win ISIS Courage Award - USAToday http://fb.me/6QwV1oEyp "], "644280912461455360": ["3:45 PM - 16 Sep 2015", "ISIS Leaders Praise Kim Davis – First Female to Win ISIS Courage Award - USAToday http://usatoday.com.co/isis-leaders-praise-kim-davis-first-female-to-win-isis-courage-award/ …"], "644285021285707776": ["4:01 PM - 16 Sep 2015", "ISIS Leaders Praise Kim Davis – First Female to Win ISIS Courage Award - USAToday http://fb.me/4NgZ2TpDY "], "644311408704778240": ["5:46 PM - 16 Sep 2015", "ISIS Leaders Praise Kim Davis – First Female to Win ISIS Courage Award - USAToday http://usatoday.com.co/isis-leaders-praise-kim-davis-first-female-to-win-isis-courage-award/ …"], "644314668895350788": ["5:59 PM - 16 Sep 2015", "ISIS Leaders Praise Kim Davis – First Female to Win ISIS Courage Award - USAToday http://usatoday.com.co/isis-leaders-praise-kim-davis-first-female-to-win-isis-courage-award/ …"], "644321224722509824": ["6:25 PM - 16 Sep 2015", "ISIS Leaders Praise Kim Davis – First Female to Win ISIS Courage Award - USAToday http://usatoday.com.co/isis-leaders-praise-kim-davis-first-female-to-win-isis-courage-award/ …"], "644322422359920641": ["6:30 PM - 16 Sep 2015", "ISIS Leaders Praise Kim Davis – First Female to Win ISIS Courage Award - USAToday http://fb.me/4tFv7r6Ad "], "644328510106955777": ["6:54 PM - 16 Sep 2015", "ISIS Leaders Praise Kim Davis – First Female to Win ISIS Courage Award - USAToday http://usatoday.com.co/isis-leaders-praise-kim-davis-first-female-to-win-isis-courage-award/ …"], "644329846848425988": ["6:59 PM - 16 Sep 2015", "ISIS Leaders Praise Kim Davis – First Female to Win ISIS Courage Award | National Report http://nationalreport.net/isis-leaders-praise-kim-davis-first-female-win-isis-courage-award/ … via @wpusta"], "644337823059963904": ["7:31 PM - 16 Sep 2015", "ISIS Leaders Praise Kim Davis – First Female to Win ISIS Courage Award - USAToday http://fb.me/3XNYnBI9g "], "644353587980562432": [null, null], "644368296389668864": ["9:32 PM - 16 Sep 2015", "ISIS Leaders Praise Kim Davis – First Female to Win ISIS Courage Award - USAToday http://fb.me/1YHvc3neJ "], "644391253736452096": ["11:03 PM - 16 Sep 2015", "ISIS Leaders Praise Kim Davis – First Female to Win ISIS Courage Award http://conservativefrontline.com/isis-leaders-praise-kim-davis-first-female-to-win-isis-courage-award/ …"], "644402418130620417": ["11:48 PM - 16 Sep 2015", "ISIS Leaders Praise Kim Davis – First Female to Win ISIS Courage Award - USAToday http://fb.me/2lG3duoSF "], "644410791811092480": ["12:21 AM - 17 Sep 2015", "Not bad... http://fb.me/41lXzjHRP "], "644435275012308992": ["1:58 AM - 17 Sep 2015", "ISIS Leaders Praise Kim Davis – First Female to Win ISIS Courage Award - USAToday http://usatoday.com.co/isis-leaders-praise-kim-davis-first-female-to-win-isis-courage-award/ …"], "644436904142839808": [null, null], "644464553829474306": [null, null], "644490583696736257": ["5:38 AM - 17 Sep 2015", "ISIS Leaders Praise Kim Davis – First Female to Win ISIS Courage Award - USAToday http://fb.me/5uytY6thz "], "644495273650053120": ["5:57 AM - 17 Sep 2015", "ISIS Leaders Praise Kim Davis – First Female to Win ISIS Courage Award - USAToday http://fb.me/4KrWlEUZd "], "644495431821455361": ["5:57 AM - 17 Sep 2015", "ISIS Leaders Praise Kim Davis – First Female to Win ISIS Courage Award - USAToday http://fb.me/3v9NYywUP "], "644511714206093313": ["7:02 AM - 17 Sep 2015", "ISIS Leaders Praise Kim Davis – First Female to Win ISIS Courage Award - USAToday http://fb.me/4tZyPqZnO "], "644556661999337472": ["10:00 AM - 17 Sep 2015", "ISIS Leaders Praise Kim Davis – First Female to Win ISIS Courage Award - USAToday http://usatoday.com.co/isis-leaders-praise-kim-davis-first-female-to-win-isis-courage-award/ …"], "644574522666954753": ["11:11 AM - 17 Sep 2015", "ISIS Leaders Praise Kim Davis – First Female to Win ISIS Courage Award - USAToday http://usatoday.com.co/isis-leaders-praise-kim-davis-first-female-to-win-isis-courage-award/ …"], "644586901484240896": ["12:01 PM - 17 Sep 2015", "ISIS Leaders Praise Kim Davis – First Female to Win ISIS Courage Award - USAToday http://usatoday.com.co/isis-leaders-praise-kim-davis-first-female-to-win-isis-courage-award/ …"], "644593965346463745": [null, null], "644606725560139776": ["1:19 PM - 17 Sep 2015", "#ISIS Leaders Praise #KimDavis – First Female to Win ISIS Courage Award - USAToday http://usatoday.com.co/isis-leaders-praise-kim-davis-first-female-to-win-isis-courage-award/ …"], "644607320534687744": ["1:22 PM - 17 Sep 2015", "ISIS Leaders Praise Kim Davis – First Female to Win ISIS Courage Award - USAToday http://usatoday.com.co/isis-leaders-praise-kim-davis-first-female-to-win-isis-courage-award/ …"], "644607979149373441": ["1:24 PM - 17 Sep 2015", "ISIS Leaders Praise Kim Davis – First Female to Win ISIS Courage Award - USAToday http://usatoday.com.co/isis-leaders-praise-kim-davis-first-female-to-win-isis-courage-award/ …"], "644660543404572672": ["4:53 PM - 17 Sep 2015", "ISIS Leaders Praise Kim Davis – First Female to Win ISIS Courage Award - USAToday -... http://tmblr.co/Zx8sPx1uRjTW2 "], "644672967738130432": ["5:43 PM - 17 Sep 2015", "ISIS Leaders Praise Kim Davis – First Female to Win ISIS Courage Award - USAToday http://usatoday.com.co/isis-leaders-praise-kim-davis-first-female-to-win-isis-courage-award/ …"], "644686919234924544": ["6:38 PM - 17 Sep 2015", "Just great. http://fb.me/3lnzFYlaU "], "644698676179415040": ["7:25 PM - 17 Sep 2015", "ISIS Leaders Praise Kim Davis – First Female to Win ISIS Courage Award - USAToday http://ln.is/usatoday.com.co/wihGe …"], "644860911237394432": ["6:09 AM - 18 Sep 2015", "ISIS Leaders Praise Kim Davis – First Female to Win ISIS Courage Award - USAToday http://fb.me/7stp9bWp0 "], "644864655731630080": ["6:24 AM - 18 Sep 2015", "Just WOW: #ISIS Leaders Praise #KimDavis – First Female to Win ISIS Courage Award - USAToday http://ln.is/usatoday.com.co/ETPEF …"], "644865447041597440": [null, null], "644930248149086208": ["10:45 AM - 18 Sep 2015", "ISIS Leaders Praise Kim Davis – First Female to Win ISIS Courage Award - USAToday http://fb.me/3hyh4mqPI "], "644943587139035136": [null, null], "644949492169445376": ["12:01 PM - 18 Sep 2015", "ISIS Leaders Praise Kim Davis – First Female to Win ISIS Courage Award - USAToday http://fb.me/7znWi3EY3 "], "644960423146483712": [null, null], "644976713403731969": ["1:50 PM - 18 Sep 2015", "@fakedansavage ISIS Leaders Praise Kim Davis – First Female to Win ISIS Courage Award - USAToday http://usatoday.com.co/isis-leaders-praise-kim-davis-first-female-to-win-isis-courage-award/ …"], "644988562987835392": ["2:37 PM - 18 Sep 2015", "ISIS Leaders Praise Kim Davis – First Female to Win ISIS Courage Award - USAToday http://fb.me/37YrkXCKc "], "645002158736297984": ["3:31 PM - 18 Sep 2015", "ISIS Leaders Praise Kim Davis – First Female to Win ISIS Courage Award - USAToday http://usatoday.com.co/isis-leaders-praise-kim-davis-first-female-to-win-isis-courage-award/ …"], "645010144720371712": ["4:02 PM - 18 Sep 2015", "ISIS Leaders Praise Kim Davis – First Female to Win ISIS Courage Award - USAToday http://fb.me/3WTM2EP8u "], "645043306536177668": ["6:14 PM - 18 Sep 2015", "No comment.... http://fb.me/1WLHX721n "], "645063232533721088": [null, null], "645070621781721088": ["8:03 PM - 18 Sep 2015", "ISIS Leaders Praise Kim Davis – First Female to Win ISIS Courage Award - USAToday http://fb.me/28IlOXfeb "], "645071227359506436": ["8:05 PM - 18 Sep 2015", "ISIS Leaders Praise Kim Davis – First Female to Win ISIS Courage Award - USAToday - http://usatoday.com.co/isis-leaders-praise-kim-davis-first-female-to-win-isis-courage-award/ …"], "645092972866867200": ["9:32 PM - 18 Sep 2015", "ISIS Leaders Praise Kim Davis – First Female to Win ISIS Courage Award - USAToday http://usatoday.com.co/isis-leaders-praise-kim-davis-first-female-to-win-isis-courage-award/ …"], "645138162751176704": ["12:31 AM - 19 Sep 2015", "ISIS Leaders Praise Kim Davis – First Female to Win ISIS Courage Award - USAToday http://usatoday.com.co/isis-leaders-praise-kim-davis-first-female-to-win-isis-courage-award/ …"], "645250632778162176": ["7:58 AM - 19 Sep 2015", "ISIS Leaders Praise Kim Davis – First Female to Win ISIS Courage Award #satire http://usatoday.com.co/isis-leaders-praise-kim-davis-first-female-to-win-isis-courage-award/ …"], "645253983804751875": [null, null], "645268377624281088": ["9:09 AM - 19 Sep 2015", "ISIS Leaders Praise Kim Davis – First Female to Win ISIS Courage Award - USAToday http://usatoday.com.co/isis-leaders-praise-kim-davis-first-female-to-win-isis-courage-award/ …"], "645327160048115712": ["1:02 PM - 19 Sep 2015", "#tcot ISIS Leaders Praise #KimDavis – First Female to Win ISIS Courage Award | National Report http://nationalreport.net/isis-leaders-praise-kim-davis-first-female-win-isis-courage-award/ … via @wpusta"], "645335661256556545": [null, null], "645348362489884672": ["2:26 PM - 19 Sep 2015", "ISIS Leaders Praise Kim Davis – First Female to Win ISIS Courage Award - USAToday http://usatoday.com.co/isis-leaders-praise-kim-davis-first-female-to-win-isis-courage-award/ …"], "645391798953754624": [null, null], "645578203541708800": ["5:40 AM - 20 Sep 2015", "ISIS Leaders Praise Kim Davis – First Female to Win ISIS Courage Award - USAToday http://usatoday.com.co/isis-leaders-praise-kim-davis-first-female-to-win-isis-courage-award/ …"], "645983655085625344": ["8:31 AM - 21 Sep 2015", "ISIS Leaders Praise Kim Davis – First Female to Win ISIS Courage Award - USAToday http://usatoday.com.co/isis-leaders-praise-kim-davis-first-female-to-win-isis-courage-award/ …"], "646433879893524480": ["2:20 PM - 22 Sep 2015", "ISIS Leaders Praise Kim Davis – First Female to Win ISIS Courage Award - USAToday http://fb.me/2UvEtcoqp "], "648136021738000384": ["7:04 AM - 27 Sep 2015", "ISIS Leaders Praise Kim Davis – First Female to Win ISIS Courage Award - USAToday http://usatoday.com.co/isis-leaders-praise-kim-davis-first-female-to-win-isis-courage-award/ …"], "649031833380876288": ["6:23 PM - 29 Sep 2015", "#Irony #satire? ISIS Leaders Praise Kim Davis – First Female to Win ISIS Courage Award - USAToday http://ln.is/usatoday.com.co/JHCpA … #StandWithPP #LGBT"], "649031843875024896": ["6:23 PM - 29 Sep 2015", "#Irony #satire? ISIS Leaders Praise Kim Davis – First Female to Win ISIS Courage Award - USAToday... http://fb.me/424yQp9Dl "], "649031849151471616": ["6:23 PM - 29 Sep 2015", "#Irony #satire? ISIS Leaders Praise Kim Davis – First Female to Win ISIS Courage Award - USAToday... http://fb.me/85Oksi0xr "], "649031852099960832": ["6:23 PM - 29 Sep 2015", "#Irony #satire? ISIS Leaders Praise Kim Davis – First Female to Win ISIS Courage Award - USAToday... http://fb.me/5AAI62mf5 "], "649031852452245504": ["6:23 PM - 29 Sep 2015", "#Irony #satire? ISIS Leaders Praise Kim Davis – First Female to Win ISIS Courage Award - USAToday... http://fb.me/7P6apryYp "]}