{"615661182012096512": ["4:20 PM - 29 Jun 2015", "PREPARE FOR INVASION: Mexico and Guatemala Partner Up! RETWEET http://conscores.org/uhi4  #USA #TeaParty #Conservatives #TeaTeams"], "618906007096434688": [null, null], "619038433466449920": ["12:00 AM - 9 Jul 2015", "RT @notalemming: Mexico is building a Southern Border Wall with Guatemala. Where is the Media? (cont) http://tl.gd/nk8hj2 "], "619292216830373889": ["4:49 PM - 9 Jul 2015", "Mexico is building it's own Southern Border Wall with Guatemala. Where is the MSM? http://ln.is/yourdaddy.net/2010/0/5sr8S … via @notalemming"], "624394113992015873": [null, null], "626875033479045120": ["3:00 PM - 30 Jul 2015", "PREPARE FOR INVASION: Mexico and Guatemala Partner Up! RETWEET http://conscores.org/uhi4  #USA #TeaParty #Conservatives #TeaTeams"], "627977301515333633": ["4:00 PM - 2 Aug 2015", "PREPARE FOR INVASION: Mexico and Guatemala Partner Up! RETWEET http://conscores.org/uhi4  #USA #TeaParty #Conservatives #TeaTeams"], "629459598143979520": ["6:10 PM - 6 Aug 2015", "PREPARE FOR INVASION: Mexico and Guatemala Partner Up! RETWEET http://conscores.org/uhi4  #USA #TeaParty #Conservatives #TeaTeams"], "630441027552288768": ["11:10 AM - 9 Aug 2015", "PREPARE FOR INVASION: Mexico and Guatemala Partner Up! RETWEET http://conscores.org/uhi4  #USA #TeaParty #Conservatives #TeaTeams"], "635104462483406850": ["8:01 AM - 22 Aug 2015", "PREPARE FOR INVASION: Mexico and Guatemala Partner Up! RETWEET http://conscores.org/uhi4  #USA #TeaParty #Conservatives #TeaTeams"], "636535336298938368": [null, null], "636535376752979968": [null, null], "636535503383195648": [null, null], "636535604159733760": [null, null], "636535806853681152": [null, null], "636536229048115200": [null, null], "636539624710500352": [null, null], "636700443490557952": [null, null], "641189441327857664": ["3:00 AM - 8 Sep 2015", "PREPARE FOR INVASION: Mexico and Guatemala Partner Up! RETWEET http://conscores.org/uhi4  #USA #TeaParty #Conservatives #TeaTeams"], "643080792638251008": ["8:16 AM - 13 Sep 2015", "Deportation, Detention and Abuse on the Mexico-Guatemala Border http://bit.ly/1FFtIgr  via @truthout"], "643083164613758976": [null, null], "643089619580383232": ["8:51 AM - 13 Sep 2015", "Deportation, Detention and Abuse on the Mexico-Guatemala Border https://shar.es/1vNZtp pic.twitter.com/uqyT1lEzRe"], "643092108690067456": [null, null], "643099027022573568": ["9:28 AM - 13 Sep 2015", "Deportation, Detention and Abuse on the Mexico-Guatemala Border https://shar.es/1vNyvx  via @sharethis"], "643101377829322752": ["9:38 AM - 13 Sep 2015", "\"Deportation, Detention and Abuse on the Mexico-Guatemala Border\" #blist #feedly http://www.truth-out.org/news/item/32763-deportation-detention-and-abuse-on-the-mexico-guatemala-border …"], "643102083470725120": [null, null], "643102367446118401": [null, null], "643104601609113600": ["9:50 AM - 13 Sep 2015", "Deportation, Detention and Abuse on the Mexico-Guatemala Border http://s.einnews.com/yQ6-sf3NH0 "], "643165022189916160": ["1:51 PM - 13 Sep 2015", "Deportation, Detention and Abuse on the Mexico-Guatemala Border https://shar.es/1vLgfh  via @sharethis"], "643180998335819776": ["2:54 PM - 13 Sep 2015", "Deportation, Detention and Abuse on the Mexico-Guatemala Border http://www.truth-out.org/news/item/32763-deportation-detention-and-abuse-on-the-mexico-guatemala-border …"], "643183700314882048": ["3:05 PM - 13 Sep 2015", "Deportation, Detention and Abuse on the Mexico-Guatemala Border http://www.truth-out.org/news/item/32763-deportation-detention-and-abuse-on-the-mexico-guatemala-border … via @truthout"], "643187320418516993": ["3:19 PM - 13 Sep 2015", "Deportation, Detention and Abuse on the Mexico-Guatemala Border https://shar.es/1vLuKK  via @sharethis"], "643194856509050880": ["3:49 PM - 13 Sep 2015", "Deportation, Detention and Abuse on the Mexico-Guatemala Border https://shar.es/1vLGCJ  via @sharethis"], "643205746272899072": ["4:32 PM - 13 Sep 2015", "Deportation, Detention and Abuse on the Mexico-Guatemala Border https://shar.es/1vLCfs  via @sharethis"], "643212977374539777": ["5:01 PM - 13 Sep 2015", "Deportation, Detention and Abuse on the Mexico-Guatemala Border https://shar.es/1vLjkU  via @sharethis"], "643213513058480129": ["5:03 PM - 13 Sep 2015", "Deportation, Detention and Abuse on the Mexico-Guatemala Border https://shar.es/1vLjUP  via @sharethis"], "643217092456480768": ["5:17 PM - 13 Sep 2015", "Deportation, Detention and Abuse on the Mexico-Guatemala Border https://shar.es/1vLeNO  via @truthout"], "643217840905015297": ["5:20 PM - 13 Sep 2015", "Deportation, Detention and Abuse on the Mexico-Guatemala Border http://www.truth-out.org/news/item/32763-deportation-detention-and-abuse-on-the-mexico-guatemala-border …"], "643229101483012096": ["6:05 PM - 13 Sep 2015", "Deportation, Detention and Abuse on the Mexico-Guatemala Border http://www.truth-out.org/news/item/32763-deportation-detention-and-abuse-on-the-mexico-guatemala-border … via @truthout"], "643234561397157888": ["6:27 PM - 13 Sep 2015", "Deportation, Detention and Abuse on the Mexico-Guatemala Border https://shar.es/1vLArN  via @sharethis"], "643242372113920000": ["6:58 PM - 13 Sep 2015", "Deportation, Detention and Abuse on the Mexico-Guatemala Border http://fb.me/45lz7olm0 "], "643266673588310017": ["8:35 PM - 13 Sep 2015", "Deportation, Detention and Abuse on the Mexico-Guatemala Border https://shar.es/1vL9VW  via @sharethis"], "643280151363452928": [null, null], "643280734615048193": ["9:30 PM - 13 Sep 2015", "Deportation, Detention and Abuse on the Mexico-Guatemala Border https://shar.es/1vLBRm  #CentAmStudies"], "643309947061706752": ["11:26 PM - 13 Sep 2015", "Deportation, Detention and Abuse on the Mexico-Guatemala Border https://shar.es/17nmWD "], "643310989903986688": ["11:31 PM - 13 Sep 2015", "Deportation, Detention and Abuse on the Mexico-Guatemala Border http://www.truth-out.org/news/item/32763-deportation-detention-and-abuse-on-the-mexico-guatemala-border …"], "643332211891015680": ["12:55 AM - 14 Sep 2015", "Deportation, Detention and Abuse on the Mexico-Guatemala Border: http://www.truth-out.org/news/item/32763-deportation-detention-and-abuse-on-the-mexico-guatemala-border …"], "643371545704972289": ["3:31 AM - 14 Sep 2015", "Deportation, Detention and Abuse on the Mexico-Guatemala Border http://fb.me/2kf0OtCbq "], "643397880364056576": ["5:16 AM - 14 Sep 2015", "Deportation, Detention and Abuse on the Mexico-Guatemala Border ~ #Truthout http://bit.ly/1LavyMt "], "643454251029495808": ["9:00 AM - 14 Sep 2015", "Deportation, Detention and Abuse on the Mexico-Guatemala Border https://shar.es/1712rV  via @sharethis"], "643454346852761600": ["9:00 AM - 14 Sep 2015", "Deportation, Detention and Abuse on the Mexico-Guatemala Border http://ow.ly/2bvd0R "], "643517631711059968": ["1:12 PM - 14 Sep 2015", "Deportation, Detention and Abuse on the Mexico-Guatemala Border https://shar.es/171Bej "], "643535113997950977": ["2:21 PM - 14 Sep 2015", "Deportation, Detention and Abuse on the Mexico-Guatemala Border http://www.truth-out.org/news/item/32763-deportation-detention-and-abuse-on-the-mexico-guatemala-border …"], "643535246361784320": ["2:22 PM - 14 Sep 2015", "Deportation, Detention and Abuse on the Mexico-Guatemala Borderhttps://shar.es/1vLeV0 "], "643559184705785856": ["3:57 PM - 14 Sep 2015", "Deportation, Detention and Abuse on the Mexico-Guatemala Border. http://www.truth-out.org/news/item/32763-deportation-detention-and-abuse-on-the-mexico-guatemala-border …"], "643680645567254528": ["11:59 PM - 14 Sep 2015", "Deportation, Detention and Abuse on the Mexico-Guatemala Border http://fb.me/3f7KDeoOT "], "643795110354919424": ["7:34 AM - 15 Sep 2015", "Deportation, Detention and Abuse on the Mexico-Guatemala Border - http://www.cjournal.info/2015/09/15/deportation-detention-and-abuse-on-the-mexico-guatemala-border/ …"], "643802099138990081": ["8:02 AM - 15 Sep 2015", "Deportation, Detention and Abuse on the Mexico-Guatemala Border http://www.occuworld.org/news/956498 "], "643804068524113920": ["8:10 AM - 15 Sep 2015", "Deportation, Detention and Abuse on the Mexico-Guatemala Border http://www.cjournal.info/2015/09/15/deportation-detention-and-abuse-on-the-mexico-guatemala-border/ …"], "643813978506838016": ["8:49 AM - 15 Sep 2015", "Deportation, Detention & Abuse on the Mexico-Guatemala Border\n#immigration\n#border\n#abuse\nhttp://www.truth-out.org/news/item/32763-deportation-detention-and-abuse-on-the-mexico-guatemala-border …"], "643814580972617728": ["8:52 AM - 15 Sep 2015", "Deportation, Detention and Abuse on the Mexico-Guatemala Border https://shar.es/170WKF  via @sharethis"], "643896625404882944": ["2:18 PM - 15 Sep 2015", "Deportation, Detention and Abuse on the Mexico-Guatemala Border http://www.truth-out.org/news/item/32763-deportation-detention-and-abuse-on-the-mexico-guatemala-border …"], "644041109283409921": [null, null], "645761707181080576": ["5:49 PM - 20 Sep 2015", "Deportation, Detention and Abuse on the Mexico-Guatemala Border https://shar.es/17tNbO  via @sharethis"], "646947406613889025": ["12:20 AM - 24 Sep 2015", "PREPARE FOR INVASION: Mexico and Guatemala Partner Up! RETWEET http://conscores.org/uhi4  #USA #TeaParty #Conservatives #TeaTeams"]}